sdata/__init__.py
sdata/client.py
sdata_client-0.1.0.dist-info/licenses/LICENSE
sdata_client-0.1.0.dist-info/METADATA
sdata_client-0.1.0.dist-info/WHEEL
sdata_client-0.1.0.dist-info/top_level.txt
sdata_client-0.1.0.dist-info/RECORD
