Metadata-Version: 2.4
Name: sdata-client
Version: 0.1.0
Summary: Python client for sdata FastAPI service.
Author: Danny Zhang
Author-email: Danny Zhang <zhangyi_ZJ@foxmail.com>
Requires-Python: >=3.11
License-File: LICENSE
Requires-Dist: requests>=2.25.0
Dynamic: license-file
